nonebot_plugin_zxpm/__init__.py
nonebot_plugin_zxpm/commands/__init__.py
nonebot_plugin_zxpm/commands/zxpm_add_group/__init__.py
nonebot_plugin_zxpm/commands/zxpm_add_group/data_source.py
nonebot_plugin_zxpm/commands/zxpm_admin_watch/__init__.py
nonebot_plugin_zxpm/commands/zxpm_ban/__init__.py
nonebot_plugin_zxpm/commands/zxpm_ban/_data_source.py
nonebot_plugin_zxpm/commands/zxpm_bot_manage/__init__.py
nonebot_plugin_zxpm/commands/zxpm_bot_manage/bot_switch.py
nonebot_plugin_zxpm/commands/zxpm_bot_manage/command.py
nonebot_plugin_zxpm/commands/zxpm_bot_manage/full_function.py
nonebot_plugin_zxpm/commands/zxpm_bot_manage/plugin.py
nonebot_plugin_zxpm/commands/zxpm_help/__init__.py
nonebot_plugin_zxpm/commands/zxpm_help/_data_source.py
nonebot_plugin_zxpm/commands/zxpm_hooks/__init__.py
nonebot_plugin_zxpm/commands/zxpm_hooks/_auth_checker.py
nonebot_plugin_zxpm/commands/zxpm_hooks/zxpm_auth_hook.py
nonebot_plugin_zxpm/commands/zxpm_hooks/zxpm_ban_hook.py
nonebot_plugin_zxpm/commands/zxpm_init/__init__.py
nonebot_plugin_zxpm/commands/zxpm_init/manager.py
nonebot_plugin_zxpm/commands/zxpm_plugin_switch/__init__.py
nonebot_plugin_zxpm/commands/zxpm_plugin_switch/_data_source.py
nonebot_plugin_zxpm/commands/zxpm_plugin_switch/command.py
nonebot_plugin_zxpm/commands/zxpm_set_admin/__init__.py
nonebot_plugin_zxpm/commands/zxpm_super_group/__init__.py
nonebot_plugin_zxpm/config.py
nonebot_plugin_zxpm/db_connect/__init__.py
nonebot_plugin_zxpm/enum.py
nonebot_plugin_zxpm/exception.py
nonebot_plugin_zxpm/extra/__init__.py
nonebot_plugin_zxpm/extra/limit.py
nonebot_plugin_zxpm/log.py
nonebot_plugin_zxpm/models/ban_console.py
nonebot_plugin_zxpm/models/bot_console.py
nonebot_plugin_zxpm/models/group_console.py
nonebot_plugin_zxpm/models/level_user.py
nonebot_plugin_zxpm/models/plugin_info.py
nonebot_plugin_zxpm/models/plugin_limit.py
nonebot_plugin_zxpm/rules.py
nonebot_plugin_zxpm/utils/build_image.py
nonebot_plugin_zxpm/utils/image_template.py
nonebot_plugin_zxpm-0.2.7.dist-info/LICENSE
nonebot_plugin_zxpm-0.2.7.dist-info/METADATA
nonebot_plugin_zxpm-0.2.7.dist-info/WHEEL
nonebot_plugin_zxpm-0.2.7.dist-info/RECORD
