Metadata-Version: 2.3
Name: nonebot-plugin-zxpm
Version: 0.2.7
Summary: 真寻的插件管理系统
License: AGPL3.0
Author: HibiKier
Author-email: 775757368@qq.com
Requires-Python: >=3.10,<4.0
Classifier: License :: Other/Proprietary License
Classifier: Programming Language :: Python :: 3
Classifier: Programming Language :: Python :: 3.10
Classifier: Programming Language :: Python :: 3.11
Classifier: Programming Language :: Python :: 3.12
Classifier: Programming Language :: Python :: 3.13
Requires-Dist: nonebot-plugin-alconna (>=0.46.3,<1.0.0)
Requires-Dist: nonebot-plugin-session (>=0.3.2)
Requires-Dist: nonebot-plugin-uninfo (>=0.6.0)
Requires-Dist: nonebot2 (>=2.3.3,<3.0.0)
Requires-Dist: pytz (>=2025.1,<2026.0)
Requires-Dist: ruamel-yaml (>=0.18.6,<0.19.0)
Requires-Dist: strenum (>=0.4.15,<0.5.0)
Requires-Dist: tortoise-orm (>=0.20,<0.21)
Requires-Dist: zhenxun-utils (>=0.2.2,<0.3.0)
Project-URL: Homepage, https://github.com/HibiKier/nonebot-plugin-zxpm
Project-URL: Repository, https://github.com/HibiKier/nonebot-plugin-zxpm
